msgraphfs/__init__.py
msgraphfs/core.py
msgraphfs_dev-0.9.dist-info/METADATA
msgraphfs_dev-0.9.dist-info/WHEEL
msgraphfs_dev-0.9.dist-info/entry_points.txt
msgraphfs_dev-0.9.dist-info/licenses/LICENSE
msgraphfs_dev-0.9.dist-info/RECORD
