Metadata-Version: 2.4
Name: msgraphfs-dev
Version: 0.9
Dynamic: Summary
Project-URL: Source, https://github.com/bolkedebruin/msgraphfs
Author-email: Laurent Mignon <laurent.mignon@acsone.eu>
License: The MIT License (MIT)
License-File: LICENSE
Classifier: Intended Audience :: Developers
Classifier: License :: OSI Approved :: MIT License
Classifier: Operating System :: OS Independent
Requires-Python: >=3.10
Requires-Dist: authlib
Requires-Dist: fsspec>=0.7.5
Requires-Dist: httpx[http2]
Provides-Extra: release
Requires-Dist: towncrier; extra == 'release'
Provides-Extra: test
Requires-Dist: coverage[toml]; extra == 'test'
Requires-Dist: keyring; extra == 'test'
Requires-Dist: pytest; extra == 'test'
Requires-Dist: pytest-asyncio; extra == 'test'
Requires-Dist: pytest-cov; extra == 'test'
Requires-Dist: requests; extra == 'test'
Requires-Dist: ruff>=0.13.0; extra == 'test'
